MANIFEST.in
README.rst
pyproject.toml
requirements.core.txt
requirements.txt
setup.py
core_module_auto_keyref_app/__init__.py
core_module_auto_keyref_app/ajax.py
core_module_auto_keyref_app/urls.py
core_module_auto_keyref_app/views.py
core_module_auto_keyref_app.egg-info/PKG-INFO
core_module_auto_keyref_app.egg-info/SOURCES.txt
core_module_auto_keyref_app.egg-info/dependency_links.txt
core_module_auto_keyref_app.egg-info/requires.txt
core_module_auto_keyref_app.egg-info/top_level.txt
core_module_auto_keyref_app/components/__init__.py
core_module_auto_keyref_app/components/auto_keyref/__init__.py
core_module_auto_keyref_app/components/auto_keyref/api.py
core_module_auto_keyref_app/components/auto_keyref/models.py
core_module_auto_keyref_app/static/core_module_auto_keyref_app/js/autokey.js
core_module_auto_keyref_app/static/core_module_auto_keyref_app/xsd/key_keyref.xsd
tests/__init__.py
tests/test_settings.py