Metadata-Version: 1.0
Name: core-module-auto-keyref-app
Version: 1.20.0
Summary: Keyref module for the parser core project
Home-page: https://github.com/usnistgov/core_module_auto_keyref_app
Author: NIST IT Lab
Author-email: itl_inquiries@nist.gov
License: UNKNOWN
Platform: UNKNOWN
